jumpserver_sync/__init__.py
jumpserver_sync/application.py
jumpserver_sync/assets.py
jumpserver_sync/listening.py
jumpserver_sync/utils.py
jumpserver_sync/workflow.py
jumpserver_sync/jumpserver/__init__.py
jumpserver_sync/jumpserver/clients.py
jumpserver_sync/providers/__init__.py
jumpserver_sync/providers/aws.py
jumpserver_sync/providers/base.py
jumpserver_sync-0.1.4.dist-info/METADATA
jumpserver_sync-0.1.4.dist-info/RECORD
jumpserver_sync-0.1.4.dist-info/WHEEL
jumpserver_sync-0.1.4.dist-info/entry_points.txt
jumpserver_sync-0.1.4.dist-info/top_level.txt
