Metadata-Version: 2.1
Name: jumpserver-sync
Version: 0.1.4
Summary: Tools to sync large amount of instance into Jumpserver.
Home-page: UNKNOWN
Author: wuwentao
Author-email: wuwentao@patsnap.com
License: MIT
Keywords: jumpserver,python,cloud,aws
Platform: UNKNOWN
Classifier: Operating System :: OS Independent
Classifier: License :: OSI Approved :: MIT License
Classifier: Programming Language :: Python :: 3.5
Classifier: Programming Language :: Python :: 3.6
Classifier: Programming Language :: Python :: 3.7
Requires-Python: >=3.5
Requires-Dist: hsettings (>=0.1)
Requires-Dist: requests
Requires-Dist: click
Requires-Dist: colorama
Requires-Dist: diskcache
Requires-Dist: boto3
Requires-Dist: pyyaml
